pygis/__init__.py
pygis/pygis.py
pygis-0.10.1.dist-info/licenses/LICENSE
pygis-0.10.1.dist-info/METADATA
pygis-0.10.1.dist-info/WHEEL
pygis-0.10.1.dist-info/top_level.txt
pygis-0.10.1.dist-info/RECORD
