Metadata-Version: 2.4
Name: pygis
Version: 0.10.1
Summary: A Python package for installing commonly used packages for GIS programming.
Author-email: Qiusheng Wu <giswqs@gmail.com>
License: MIT license
Project-URL: Homepage, https://github.com/opengeos/pygis
Keywords: pygis
Classifier: Development Status :: 2 - Pre-Alpha
Classifier: Intended Audience :: Developers
Classifier: License :: OSI Approved :: MIT License
Classifier: Natural Language :: English
Classifier: Programming Language :: Python :: 3
Classifier: Programming Language :: Python :: 3.9
Classifier: Programming Language :: Python :: 3.10
Classifier: Programming Language :: Python :: 3.11
Classifier: Programming Language :: Python :: 3.12
Requires-Python: >=3.9
License-File: LICENSE
Requires-Dist: bash_kernel
Requires-Dist: duckdb
Requires-Dist: duckdb-engine
Requires-Dist: ffmpeg-python
Requires-Dist: geeadd
Requires-Dist: geemap>=0.35.3
Requires-Dist: geopandas
Requires-Dist: ipykernel
Requires-Dist: jupysql
Requires-Dist: jupyter-server-proxy
Requires-Dist: leafmap>=0.48.0
Requires-Dist: mapclassify
Requires-Dist: maplibre
Requires-Dist: mapwidget
Requires-Dist: numpy
Requires-Dist: pandas
Requires-Dist: planetary-computer
Requires-Dist: pmtiles
Requires-Dist: pooch
Requires-Dist: shapely
Requires-Dist: solara
Requires-Dist: voila
Requires-Dist: voila-topbar
Requires-Dist: whiteboxgui
Requires-Dist: xarray
Provides-Extra: raster
Requires-Dist: rasterio; extra == "raster"
Requires-Dist: rioxarray; extra == "raster"
Requires-Dist: earthaccess; extra == "raster"
Requires-Dist: hypercoast; extra == "raster"
Requires-Dist: geedim; extra == "raster"
Requires-Dist: py3dep; extra == "raster"
Provides-Extra: lidar
Requires-Dist: laspy[laszip,lazrs]; extra == "lidar"
Requires-Dist: pyntcloud[LAS]; extra == "lidar"
Requires-Dist: pyvista[all]; extra == "lidar"
Provides-Extra: vector
Requires-Dist: overturemaps; extra == "vector"
Requires-Dist: fiona; extra == "vector"
Provides-Extra: plot
Requires-Dist: pygis[all]; extra == "plot"
Requires-Dist: kaleido; extra == "plot"
Provides-Extra: all
Requires-Dist: pygis[lidar,raster,vector]; extra == "all"
Dynamic: license-file
